async_obj/__init__.py
async_obj/async_obj.py
async_obj-1.0.2.dist-info/licenses/LICENSE
async_obj-1.0.2.dist-info/METADATA
async_obj-1.0.2.dist-info/WHEEL
async_obj-1.0.2.dist-info/top_level.txt
async_obj-1.0.2.dist-info/RECORD
