Metadata-Version: 2.4
Name: async_obj
Version: 1.0.2
Summary: A simple wrapper to run any function asynchronously in a dedicated thread. Supports standalone functions and functions inside classes as well as result collection and exception propagation.
Author: Gun Deniz Akkoc
License-Expression: Apache-2.0
Project-URL: Repository, https://github.com/gunakkoc/async_obj
Project-URL: Issues, https://github.com/gunakkoc/async_obj/issues
Keywords: asynchronous,async,asyncio,concurrency,concurrent,thread,threading,parallelization,non-blocking,wrapper,function,class
Classifier: Development Status :: 4 - Beta
Classifier: Intended Audience :: Developers
Classifier: Programming Language :: Python :: 3
Classifier: Programming Language :: Python :: 3.8
Classifier: Programming Language :: Python :: 3.9
Classifier: Programming Language :: Python :: 3.10
Classifier: Programming Language :: Python :: 3.11
Classifier: Programming Language :: Python :: 3.12
Classifier: Programming Language :: Python :: 3.13
Classifier: Topic :: Software Development :: Libraries :: Python Modules
Requires-Python: >=3.8
License-File: LICENSE
Dynamic: license-file
